MANIFEST.in
README.md
requirements.txt
setup.cfg
setup.py
pyramid_swagger_spec/__init__.py
pyramid_swagger_spec/errors.py
pyramid_swagger_spec/namespace.py
pyramid_swagger_spec/schema.py
pyramid_swagger_spec/swagger.py
pyramid_swagger_spec/validator.py
pyramid_swagger_spec.egg-info/PKG-INFO
pyramid_swagger_spec.egg-info/SOURCES.txt
pyramid_swagger_spec.egg-info/dependency_links.txt
pyramid_swagger_spec.egg-info/requires.txt
pyramid_swagger_spec.egg-info/top_level.txt