Metadata-Version: 1.1
Name: pyramid-swagger-spec
Version: 0.0.11
Summary: Defines APIs, generates a Swagger specification, and validates inputs
Home-page: https://github.com/ActiDoo/pyramid_swagger_spec
Author: Marcel Sander
Author-email: marcel@actidoo.com
License: BSD
Download-URL: https://github.com/ActiDoo/pyramid_swagger_spec/tarball/0.0.11
Platform: UNKNOWN
Classifier: Development Status :: 3 - Alpha
Classifier: Intended Audience :: Developers
Classifier: Programming Language :: Python :: 3
